tensorflow_probability/__init__.py
tensorflow_probability/python/__init__.py
tensorflow_probability/python/version.py
tensorflow_probability/python/bijectors/__init__.py
tensorflow_probability/python/bijectors/absolute_value.py
tensorflow_probability/python/bijectors/ascending.py
tensorflow_probability/python/bijectors/batch_normalization.py
tensorflow_probability/python/bijectors/bijector.py
tensorflow_probability/python/bijectors/blockwise.py
tensorflow_probability/python/bijectors/categorical_to_discrete.py
tensorflow_probability/python/bijectors/chain.py
tensorflow_probability/python/bijectors/cholesky_outer_product.py
tensorflow_probability/python/bijectors/cholesky_to_inv_cholesky.py
tensorflow_probability/python/bijectors/composition.py
tensorflow_probability/python/bijectors/correlation_cholesky.py
tensorflow_probability/python/bijectors/cumsum.py
tensorflow_probability/python/bijectors/discrete_cosine_transform.py
tensorflow_probability/python/bijectors/exp.py
tensorflow_probability/python/bijectors/expm1.py
tensorflow_probability/python/bijectors/ffjord.py
tensorflow_probability/python/bijectors/fill_scale_tril.py
tensorflow_probability/python/bijectors/fill_triangular.py
tensorflow_probability/python/bijectors/frechet_cdf.py
tensorflow_probability/python/bijectors/generalized_pareto.py
tensorflow_probability/python/bijectors/gev_cdf.py
tensorflow_probability/python/bijectors/glow.py
tensorflow_probability/python/bijectors/gompertz_cdf.py
tensorflow_probability/python/bijectors/gumbel_cdf.py
tensorflow_probability/python/bijectors/householder.py
tensorflow_probability/python/bijectors/identity.py
tensorflow_probability/python/bijectors/inline.py
tensorflow_probability/python/bijectors/invert.py
tensorflow_probability/python/bijectors/iterated_sigmoid_centered.py
tensorflow_probability/python/bijectors/joint_map.py
tensorflow_probability/python/bijectors/kumaraswamy_cdf.py
tensorflow_probability/python/bijectors/lambertw_transform.py
tfp_nightly-0.26.0.dev20260201.dist-info/METADATA
tfp_nightly-0.26.0.dev20260201.dist-info/WHEEL
tfp_nightly-0.26.0.dev20260201.dist-info/top_level.txt
tfp_nightly-0.26.0.dev20260201.dist-info/RECORD
