Metadata-Version: 2.1
Name: tfp-nightly
Version: 0.26.0.dev20260201
Summary: Probabilistic modeling and statistical inference in TensorFlow
Home-page: http://github.com/tensorflow/probability
Author: Google LLC
Author-email: no-reply@google.com
License: Apache 2.0
Keywords: tensorflow probability statistics bayesian machine learning
Classifier: Development Status :: 4 - Beta
Classifier: Intended Audience :: Developers
Classifier: Intended Audience :: Education
Classifier: Intended Audience :: Science/Research
Classifier: License :: OSI Approved :: Apache Software License
Classifier: Programming Language :: Python :: 3
Classifier: Programming Language :: Python :: 3.9
Classifier: Programming Language :: Python :: 3.10
Classifier: Programming Language :: Python :: 3.11
Classifier: Programming Language :: Python :: 3.12
Classifier: Topic :: Scientific/Engineering
Classifier: Topic :: Scientific/Engineering :: Mathematics
Classifier: Topic :: Scientific/Engineering :: Artificial Intelligence
Classifier: Topic :: Software Development
Classifier: Topic :: Software Development :: Libraries
Classifier: Topic :: Software Development :: Libraries :: Python Modules
Requires-Python: >=3.9
Requires-Dist: absl-py
Requires-Dist: six>=1.10.0
Requires-Dist: numpy>=1.13.3
Requires-Dist: decorator
Requires-Dist: cloudpickle>=1.3
Requires-Dist: gast>=0.3.2
Requires-Dist: dm-tree
Provides-Extra: jax
Requires-Dist: jax; extra == "jax"
Requires-Dist: jaxlib; extra == "jax"
Provides-Extra: tf
Requires-Dist: tf-nightly; extra == "tf"
Requires-Dist: tf-keras-nightly; extra == "tf"
Provides-Extra: tfds
Requires-Dist: tfds-nightly; extra == "tfds"
